data_transformation_library/__init__.py
data_transformation_library/module.py
data_transform_lib_turing-1.1.dist-info/METADATA
data_transform_lib_turing-1.1.dist-info/WHEEL
data_transform_lib_turing-1.1.dist-info/RECORD
