Metadata-Version: 2.1
Name: data_transform_lib_turing
Version: 1.1
Summary: 3 functions for data transformation
Author: Lukas Miliauskas
Requires-Python: >=3.12,<4.0
Classifier: Programming Language :: Python :: 3
Classifier: Programming Language :: Python :: 3.12
Requires-Dist: numpy (>=2.0.1,<3.0.0)
